markdown_javadoc_references/__init__.py
markdown_javadoc_references/docsite/docsite.py
markdown_javadoc_references/docsite/jdk8.py
markdown_javadoc_references/docsite/jdk9.py
markdown_javadoc_references/docsite/util.py
markdown_javadoc_references/entities.py
markdown_javadoc_references/extension.py
markdown_javadoc_references/processor/autolink.py
markdown_javadoc_references/processor/javadoc.py
markdown_javadoc_references/reference.py
markdown_javadoc_references/resolver.py
markdown_javadoc_references/util.py
markdown_javadoc_references-0.6.3.dist-info/METADATA
markdown_javadoc_references-0.6.3.dist-info/WHEEL
markdown_javadoc_references-0.6.3.dist-info/licenses/LICENSE
markdown_javadoc_references-0.6.3.dist-info/RECORD
