Metadata-Version: 2.4
Name: markdown_javadoc_references
Version: 0.6.3
Summary: A Markdown extension that makes it easy to reference Javadocs
License-Expression: MIT
License-File: LICENSE
Keywords: markdown,markdown-extension,mkdocs,mkdocs-plugin,documentation,javadoc,java,references,links,markdown links,javadoc links,java-references,api-docs,docs,doc-links
Author: Nick Hensel
Requires-Python: >=3.9
Classifier: Environment :: Web Environment
Classifier: Framework :: MkDocs
Classifier: Intended Audience :: Developers
Classifier: License :: OSI Approved :: MIT License
Classifier: Operating System :: OS Independent
Classifier: Programming Language :: Python
Classifier: Programming Language :: Python :: 3
Classifier: Programming Language :: Python :: 3.9
Classifier: Programming Language :: Python :: 3.10
Classifier: Programming Language :: Python :: 3.11
Classifier: Programming Language :: Python :: 3.12
Classifier: Programming Language :: Python :: 3.13
Classifier: Topic :: Documentation
Classifier: Topic :: Documentation :: Sphinx
Classifier: Topic :: Software Development :: Documentation
Classifier: Topic :: Text Processing :: Markup
Classifier: Typing :: Typed
Provides-Extra: mkdocs
Requires-Dist: beautifulsoup4
Requires-Dist: markdown
Requires-Dist: mkdocs ; extra == "mkdocs"
Requires-Dist: requests
Project-URL: github, https://github.com/Goldmensch/pymarkdown-java-references
